Workbook
Name Avions: Convertisseurs!#REF!
Name Biocombustibles: Convertisseurs!#REF!
Name Carburant: Convertisseurs!#REF!
Name CFC_hors_kyoto: Convertisseurs!#REF!
Name chaussée: Convertisseurs!#REF!
Name Combustibles: Convertisseurs!#REF!
Name CONSOMMABLES_ET_MATERIAUX: 'Campus site 1'!$A$338:$T$468
Name construction_surface: Convertisseurs!#REF!
Name Déchets_carton_annuels: #REF!
Name Déchets_carton_par_jour__kg: #REF!
Name DECHETS_DIRECTS: 'Campus site 1'!$A$608:$T$684
Name Déchets_journeaux_dans_l_année: #REF!
Name Déchets_journeaux_par_jour: #REF!
Name Déchets_papier_du_forum__tonnes: #REF!
Name Déchets_plastiques_annuels: #REF!
Name Déchets_plastiques_par_jour__kg: #REF!
Name Densité_de_l_eau__kg_m3: #REF!
Name DEPLACEMENT_PERSONNES: 'Campus site 1'!$A$206:$S$336
Name Distance_moyenne_en_TGV_longue_distance__km: #REF!
Name Eaux_usées_annuelles__m3: #REF!
Name Effectif_total: #REF!
Name Electricite_m2: Convertisseurs!#REF!
Name Electricite_pays: Convertisseurs!#REF!
Name Electricite_producteur: Convertisseurs!#REF!
Name Extrapolation_personnes_prenant_le_TGV_régulièrement: #REF!
Name FRET: 'Campus site 1'!$A$101:$W$204
Name fret_ferroviaire: Convertisseurs!#REF!
Name fret_fluvial_bassin: Convertisseurs!#REF!
Name fret_fluvial_bateau: Convertisseurs!#REF!
Name fret_maritime: Convertisseurs!#REF!
Name fret_routier: Convertisseurs!#REF!
Name Halocarbures_Kyoto: Convertisseurs!#REF!
Name IMMOBILISATIONS: 'Campus site 1'!$A$685:$T$780
Name INIES: Convertisseurs!#REF!
Name Largeur_feuille__m: #REF!
Name Longueur_feuille__m: #REF!
Name matériaux_construction_batiments: Convertisseurs!#REF!
Name Metaux: Convertisseurs!#REF!
Name métaux: Convertisseurs!#REF!
Name Nombre_de_canettes_par_jour: #REF!
Name Nombre_de_déplacements_par_semaine: #REF!
Name Nombre_de_feuilles_jetées_dans_l_année: #REF!
Name Nombre_de_feuilles_jetées_pour_deux_semaines: #REF!
Name Nombre_de_feuilles_par_ramette: #REF!
Name Nombre_de_jour_par_semaine_sur_le_campus: #REF!
Name Nombre_de_ramettes: #REF!
Name Nombre_de_semaines: #REF!
Name Nombre_de_semaines_sur_le_campus: #REF!
Name Nombre_de_trajets_TGV_longue_distance_par_personne: #REF!
Name Nomrbe_de_répondants: #REF!
Name Papier: Convertisseurs!#REF!
Name personnes_train: '[1]Facteurs d''émission'!$A$452:$A$473
Name plastique: Convertisseurs!#REF!
Name Plastiques: Convertisseurs!#REF!
Name Poids_d_une_canette_vide__g: #REF!
Name Poids_des_feuilles_jetées_dans_l_année__tonnes: #REF!
Name Poids_feuille_par_surface__g_m²: #REF!
Name Pourcentage_de_répondants: #REF!
Name produit_agricole: Convertisseurs!#REF!
Name produit_chimique: Convertisseurs!#REF!

Sheet Accueil
E2: Tableur PCC - Projet Carbone Campus
C5: A quoi sert cet outil ?
C6: Cet outil est utilisé dans le cadre du Projet Carbone Campus pour réaliser le bilan carbone d'un campus. Si quelqu'un vous a transmis ce tableur sans formation préalable, nous vous recommandons de contacter le Réseau Français des Etudiants pour le Développement Durable (REFEDD) : http://refedd.org/projet-carbone-campus/ L’outil permet de comptabiliser les émissions de gaz à effet de serre d'un campus. La finalité de l’outil consiste à introduire la méthode du Bilan Carbone aux étudiants et les assister dans la réalisation d'un plan d'action auprès de la direction de l'établissement et autres parties prenantes. Cet outil n'a pas pour vocation à être utilisé pour un Bilan Carbone® officiel. Pour obtenir le tableur officiel, se rapprocher de l'Association Bilan Carbone (ABC) : https://www.associationbilancarbone.fr/
C10: Comment utiliser cet outil?
C11: L'onglet principal (Campus site) permet : - de renseigner les différentes quantités impactant le campus, sur les différents poste : de "sources fixes" à "immobilisations" - d'en déduire son impact climatique en eq-CO2 - de se fixer des objectifs de réduction d'émissions de GES L'onglet Facteur d'émission permet de vérifier les facteurs d'émissions utilisés dans l'onglet principal et d'en ajouter de nouveaux. L'onglet Totalisateur permet de voir le résultat de son bilan, et poursuivre la démarche itérative. L'onglet Convertisseurs permet de faire quelques conversions d'unités, et d'estimer les fuites de fluides frigorigènes. Une notice détaillée de l'outil est disponible.
B15: Le tableur PCC est à mis à disposition selon les termes de
B16: la licence Creative Commons Attribution 4.0 Internationale
B19: La version de référence de cet outil est disponible sur le site web d'Avenir Climatique.
B21: Pour toute remarque ou question concernant cette outil, merci de nous contacter : contact@avenirclimatique.org

Sheet Facteurs d'émission
B1: Catégorie | C1: Sous catégorie | D1: Source d'émission | E1: Facteur d'émission (eq CO2) | F1: Unité | G1: Incertitude (%) | H1: Dernière mise à jour | I1: Période de validité | J1: Source
B2: SOURCES FIXES | C2: Combustible | D2: Fioul domestique | E2: 0.32 | F2: kgCO2e/kWh PCI | G2: 0.05 | H2: 45644 | I2: 43070 | J2: Base Empreinte ADEME
B3: SOURCES FIXES | C3: Combustible | D3: Fioul lourd | E3: 0.32 | F3: kgCO2e/kWh PCI | G3: 0.05 | H3: 45644 | I3: 43435 | J3: Base Empreinte ADEME
B4: SOURCES FIXES | C4: Combustible | D4: Gaz Naturel | E4: 0.24 | F4: kgCO2e/kWh PCI | G4: 0.05 | H4: 45644 | I4: 45716 | J4: Base Empreinte ADEME
B5: SOURCES FIXES | C5: Combustible | D5: Bois granulé / Combustion en chaudière / Label E+ | E5: 0.027 | F5: kgCO2e/kWh | H5: 45278 | I5: 44166 | J5: Base Empreinte ADEME
B6: SOURCES FIXES | C6: Combustible | D6: A COMPLETER DANS FACTEURS D'EMISSIONS | L6: Pour toute question ou pour trouver de nouveaux facteurs d'émissions :
B7: SOURCES FIXES | C7: Combustible | D7: A COMPLETER DANS FACTEURS D'EMISSIONS
B8: SOURCES FIXES | C8: Combustible | D8: A COMPLETER DANS FACTEURS D'EMISSIONS
B9: SOURCES FIXES | C9: Combustible | D9: A COMPLETER DANS FACTEURS D'EMISSIONS | L9: https://base-empreinte.ademe.fr/
B10: SOURCES FIXES | C10: Combustible | D10: A COMPLETER DANS FACTEURS D'EMISSIONS
B11: SOURCES FIXES | C11: Electricité | D11: Mix électrique français (année 2024) | E11: 0.0519 | F11: kgCO2e/kWh | G11: 0.1 | H11: 45644 | I11: 45627 | J11: Base Empreinte ADEME
B12: SOURCES FIXES | C12: Electricité | D12: Mix électrique français (année 2021) | E12: 0.0569 | F12: kgCO2e/kWh | G12: 0.1 | H12: 44548 | I12: 44531 | J12: Base Empreinte ADEME
B13: SOURCES FIXES | C13: Electricité | D13: Mix électrique français (année 2017) | E13: 0.056 | F13: kgCO2e/kWh | G13: 0.1 | H13: 43087 | I13: 43070 | J13: Base Empreinte ADEME
B14: SOURCES FIXES | C14: Electricité | D14: Mix électrique allemand (année 2017) | E14: 0.46 | F14: kgCO2e/kWh | G14: 0.1 | H14: 43087 | I14: 43070 | J14: Base Empreinte ADEME
B15: SOURCES FIXES | C15: Electricité | D15: Mix électrique européen (année 2017) | E15: 0.42 | F15: kgCO2e/kWh | G15: 0.1 | H15: 43087 | I15: 43070 | J15: Base Empreinte ADEME
B16: SOURCES FIXES | C16: Electricité | D16: A COMPLETER DANS FACTEURS D'EMISSIONS
B17: SOURCES FIXES | C17: Gaz frigorifique | D17: R134a | E17: 1530 | F17: kgCO2e/kg | G17: 0.3 | H17: 45556 | J17: GIEC AR6
B18: SOURCES FIXES | C18: Gaz frigorifique | D18: R22 (gaz interdit à la vente et à l'utilisation depuis 2015) | E18: 1960 | F18: kgCO2e/kg | G18: 0.3 | H18: 45556 | J18: GIEC AR6
B19: SOURCES FIXES | C19: Gaz frigorifique | D19: R32 | E19: 770 | F19: kgCO2e/kg | G19: 0.3 | H19: 45556 | J19: GIEC AR6
B20: SOURCES FIXES | C20: Gaz frigorifique | D20: R404a (gaz interdit à la vente depuis 2020 et à l'utilisation depuis 2025) | E20: 4730 | F20: kgCO2e/kg | G20: 0.3 | H20: 45556 | J20: Base Empreinte ADEME
B21: SOURCES FIXES | C21: Gaz frigorifique | D21: R407c | E21: 1910 | F21: kgCO2e/kg | G21: 0.3 | H21: 45556 | J21: Base Empreinte ADEME
B22: SOURCES FIXES | C22: Gaz frigorifique | D22: R410a | E22: 2260 | F22: kgCO2e/kg | G22: 0.3 | H22: 45556 | J22: Base Empreinte ADEME
B23: SOURCES FIXES | C23: Gaz frigorifique | D23: R427a | E23: 2400 | F23: kgCO2e/kg | G23: 0.3 | H23: 45556 | J23: Base Empreinte ADEME
B24: SOURCES FIXES | C24: Gaz frigorifique | D24: R507a | E24: 2640 | F24: kgCO2e/kg | G24: 0.3 | H24: 45556 | J24: Base Empreinte ADEME
B25: SOURCES FIXES | C25: Gaz frigorifique | D25: A COMPLETER DANS FACTEURS D'EMISSIONS
B26: SOURCES FIXES | C26: Gaz frigorifique | D26: A COMPLETER DANS FACTEURS D'EMISSIONS
B27: SOURCES FIXES | C27: Gaz frigorifique | D27: A COMPLETER DANS FACTEURS D'EMISSIONS
B28: SOURCES FIXES | C28: Gaz frigorifique | D28: A COMPLETER DANS FACTEURS D'EMISSIONS
B29: SOURCES FIXES | C29: Gaz frigorifique | D29: A COMPLETER DANS FACTEURS D'EMISSIONS
B30: FRET | C30: Fret routier | D30: Camion porteur - Diesel avec 7% biodiesel, PTAC 20T | E30: 0.17 | F30: kgCO2e/tonne.km | G30: 0.7 | H30: 46009 | I30: 46357 | J30: Base Empreinte ADEME
B31: FRET | C31: Fret routier | D31: Camion porteur - Diesel avec 7% biodiesel, PTAC 7,5T | E31: 0.4 | F31: kgCO2e/tonne.km | G31: 0.7 | H31: 46009 | I31: 46357 | J31: Base Empreinte ADEME
B32: FRET | C32: Fret routier | D32: Camion porteur - Diesel avec 7% biodiesel, PTRA 26T | E32: 0.14 | F32: kgCO2e/tonne.km | G32: 0.7 | H32: 46009 | I32: 46357 | J32: Base Empreinte ADEME
B33: FRET | C33: Fret routier | D33: Camion porteur - Diesel avec 7% biodiesel, PTRA 40T | E33: 0.087 | F33: kgCO2e/tonne.km | G33: 0.7 | H33: 46009 | I33: 46357 | J33: Base Empreinte ADEME
B34: FRET | C34: Fret routier | D34: Véhicule Utilitaire Léger - Essence | E34: 0.92 | F34: kgCO2e/tonne.km | G34: 0.7 | H34: 46009 | I34: 46357 | J34: Base Empreinte ADEME
B35: FRET | C35: Fret routier | D35: A COMPLETER DANS FACTEURS D'EMISSIONS
B36: FRET | C36: Fret routier | D36: A COMPLETER DANS FACTEURS D'EMISSIONS
B37: FRET | C37: Fret routier | D37: A COMPLETER DANS FACTEURS D'EMISSIONS
B38: FRET | C38: Fret routier | D38: A COMPLETER DANS FACTEURS D'EMISSIONS
B39: FRET | C39: Fret routier | D39: A COMPLETER DANS FACTEURS D'EMISSIONS
B40: FRET | C40: Fret aérien | D40: Avion (marchandises) - plus de 220 sièges, trajet de 1000 - 2000 km avec trainées | E40: 2.36 | F40: kgCO2e/tonne.km | G40: 0.7 | H40: 45914 | I40: 46357 | J40: Base Empreinte ADEME
B41: FRET | C41: Fret aérien | D41: Avion (marchandises) - plus de 220 sièges, trajet de 2000 - 5000 km | E41: 1.69 | F41: kgCO2e/tonne.km | G41: 0.7 | H41: 45914 | I41: 46357 | J41: Base Empreinte ADEME
B42: FRET | C42: Fret aérien | D42: Avion (marchandises) - plus de 220 sièges, trajet > 5000 km | E42: 1.51 | F42: kgCO2e/tonne.km | G42: 0.7 | H42: 45914 | I42: 46357 | J42: Base Empreinte ADEME
B43: FRET | C43: Fret aérien | D43: A COMPLETER DANS FACTEURS D'EMISSIONS
B44: FRET | C44: Fret aérien | D44: A COMPLETER DANS FACTEURS D'EMISSIONS
B45: FRET | C45: Fret aérien | D45: A COMPLETER DANS FACTEURS D'EMISSIONS
B46: FRET | C46: Fret aérien | D46: A COMPLETER DANS FACTEURS D'EMISSIONS
B47: FRET | C47: Fret aérien | D47: A COMPLETER DANS FACTEURS D'EMISSIONS
B48: FRET | C48: Fret ferroviaire | D48: Train de marchandises (Europe) - Gazole | E48: 0.0613 | F48: kgCO2e/tonne.km | H48: 45914 | I48: 46357 | J48: Base Empreinte ADEME
B49: FRET | C49: Fret ferroviaire | D49: Train de marchandises (France) - motorisation électrique, chargement dense | E49: 0.00404 | F49: kgCO2e/tonne.km | G49: 0.7 | H49: 45914 | I49: 46357 | J49: Base Empreinte ADEME
B50: FRET | C50: Fret ferroviaire | D50: A COMPLETER DANS FACTEURS D'EMISSIONS
B51: FRET | C51: Fret ferroviaire | D51: A COMPLETER DANS FACTEURS D'EMISSIONS
B52: FRET | C52: Fret ferroviaire | D52: A COMPLETER DANS FACTEURS D'EMISSIONS
B53: FRET | C53: Fret ferroviaire | D53: A COMPLETER DANS FACTEURS D'EMISSIONS
B54: FRET | C54: Fret ferroviaire | D54: A COMPLETER DANS FACTEURS D'EMISSIONS
B55: FRET | C55: Fret fluvial / maritime | D55: Porte-conteneurs (moyenne mondiale) | E55: 0.0102 | F55: kgCO2e/tonne.km | H55: 45933 | J55: Base Empreinte ADEME
B56: FRET | C56: Fret fluvial / maritime | D56: Porte-conteneurs frigorifique (moyenne mondiale) | E56: 0.0227 | F56: kgCO2e/tonne.km | H56: 45933 | J56: Base Empreinte ADEME
B57: FRET | C57: Fret fluvial / maritime | D57: A COMPLETER DANS FACTEURS D'EMISSIONS
B58: FRET | C58: Fret fluvial / maritime | D58: A COMPLETER DANS FACTEURS D'EMISSIONS
B59: FRET | C59: Fret fluvial / maritime | D59: A COMPLETER DANS FACTEURS D'EMISSIONS
B60: FRET | C60: Fret fluvial / maritime | D60: A COMPLETER DANS FACTEURS D'EMISSIONS
B61: FRET | C61: Fret fluvial / maritime | D61: A COMPLETER DANS FACTEURS D'EMISSIONS
B62: DEPLACEMENT DE PERSONNES | C62: Automobile | D62: Voiture particulière (moyenne; essence) | E62: 0.27 | F62: kgCO2e/km | G62: 0.6 | H62: 45738 | I62: 46357 | J62: Base Empreinte ADEME
B63: DEPLACEMENT DE PERSONNES | C63: Automobile | D63: Voiture particulière (moyenne; diesel) | E63: 0.24 | F63: kgCO2e/km | G63: 0.6 | H63: 45738 | I63: 46357 | J63: Base Empreinte ADEME
B64: DEPLACEMENT DE PERSONNES | C64: Automobile | D64: A COMPLETER DANS FACTEURS D'EMISSIONS
B65: DEPLACEMENT DE PERSONNES | C65: Automobile | D65: A COMPLETER DANS FACTEURS D'EMISSIONS
B66: DEPLACEMENT DE PERSONNES | C66: Automobile | D66: A COMPLETER DANS FACTEURS D'EMISSIONS
B67: DEPLACEMENT DE PERSONNES | C67: Automobile | D67: A COMPLETER DANS FACTEURS D'EMISSIONS
B68: DEPLACEMENT DE PERSONNES | C68: Automobile | D68: A COMPLETER DANS FACTEURS D'EMISSIONS
B69: DEPLACEMENT DE PERSONNES | C69: Transports urbains | D69: Autobus - agglomérations de 100 000 à 250 000 habitants | E69: 0.15 | F69: kgCO2e/passager.km | G69: 0.6 | H69: 43357 | I69: 44652 | J69: Base Empreinte ADEME
B70: DEPLACEMENT DE PERSONNES | C70: Transports urbains | D70: Autobus - agglomérations de moins de 100 000 habitants | E70: 0.2 | F70: kgCO2e/passager.km | G70: 0.6 | H70: 43357 | I70: 44652 | J70: Base Empreinte ADEME
B71: DEPLACEMENT DE PERSONNES | C71: Transports urbains | D71: Autobus - agglomérations de plus de 250 000 habitants | E71: 0.15 | F71: kgCO2e/passager.km | G71: 0.6 | H71: 43357 | I71: 44652 | J71: Base Empreinte ADEME
B72: DEPLACEMENT DE PERSONNES | C72: Transports urbains | D72: Métro - Ile de France | E72: 0.0044 | F72: kgCO2e/passager.km | G72: 0.2 | H72: 43375 | I72: 46357 | J72: Base Empreinte ADEME
B73: DEPLACEMENT DE PERSONNES | C73: Transports urbains | D73: RER - Ile de France | E73: 0.0098 | F73: kgCO2e/passager.km | G73: 0.2 | H73: 43375 | I73: 45383 | J73: Base Empreinte ADEME
B74: DEPLACEMENT DE PERSONNES | C74: Transports urbains | D74: Tramway - - agglomérations de 100 000 à 250 000 habitants | E74: 0.005 | F74: kgCO2e/passager.km | G74: 0.6 | H74: 43375 | I74: 44287 | J74: Base Empreinte ADEME
B75: DEPLACEMENT DE PERSONNES | C75: Transports urbains | D75: A COMPLETER DANS FACTEURS D'EMISSIONS
B76: DEPLACEMENT DE PERSONNES | C76: Transports urbains | D76: A COMPLETER DANS FACTEURS D'EMISSIONS
B77: DEPLACEMENT DE PERSONNES | C77: Transports urbains | D77: A COMPLETER DANS FACTEURS D'EMISSIONS
B78: DEPLACEMENT DE PERSONNES | C78: Transports urbains | D78: A COMPLETER DANS FACTEURS D'EMISSIONS
B79: DEPLACEMENT DE PERSONNES | C79: Transports urbains | D79: A COMPLETER DANS FACTEURS D'EMISSIONS
B80: DEPLACEMENT DE PERSONNES | C80: Deux roues | D80: Moto - cylindrée inf. à 250 cm³, essence, zone urbaine | E80: 0.083 | F80: kgCO2e/km | G80: 0.6 | H80: 45183 | I80: 46357 | J80: Base Empreinte ADEME
B81: DEPLACEMENT DE PERSONNES | C81: Deux roues | D81: Moto - cylindrée sup. à 250 cm³, essence, zone urbaine | E81: 0.22 | F81: kgCO2e/km | G81: 0.6 | H81: 45183 | I81: 46357 | J81: Base Empreinte ADEME
B82: DEPLACEMENT DE PERSONNES | C82: Deux roues | D82: A COMPLETER DANS FACTEURS D'EMISSIONS
B83: DEPLACEMENT DE PERSONNES | C83: Deux roues | D83: A COMPLETER DANS FACTEURS D'EMISSIONS
B84: DEPLACEMENT DE PERSONNES | C84: Deux roues | D84: A COMPLETER DANS FACTEURS D'EMISSIONS
B85: DEPLACEMENT DE PERSONNES | C85: Deux roues | D85: A COMPLETER DANS FACTEURS D'EMISSIONS
B86: DEPLACEMENT DE PERSONNES | C86: Deux roues | D86: A COMPLETER DANS FACTEURS D'EMISSIONS
B87: DEPLACEMENT DE PERSONNES | C87: Ferroviaire | D87: Intercités | E87: 0.0075 | F87: kgCO2e/passager.km | G87: 0.2 | H87: 43181 | I87: 45383 | J87: Base Empreinte ADEME
B88: DEPLACEMENT DE PERSONNES | C88: Ferroviaire | D88: TGV | E88: 0.0029 | F88: kgCO2e/passager.km | G88: 0.2 | H88: 43181 | I88: 45627 | J88: Base Empreinte ADEME
B89: DEPLACEMENT DE PERSONNES | C89: Ferroviaire | D89: TER - Traction moyenne | E89: 0.0277 | F89: kgCO2e/passager.km | G89: 0.6 | H89: 43181 | I89: 45627 | J89: Base Empreinte ADEME
B90: DEPLACEMENT DE PERSONNES | C90: Ferroviaire | D90: Train en Allemagne | E90: 0.0668 | F90: kgCO2e/passager.km | G90: 0.2 | H90: 42085 | I90: 43070 | J90: Base Empreinte ADEME
B91: DEPLACEMENT DE PERSONNES | C91: Ferroviaire | D91: Train en Belgique | E91: 0.0484 | F91: kgCO2e/passager.km | G91: 0.2 | H91: 42085 | I91: 43070 | J91: Base Empreinte ADEME
B92: DEPLACEMENT DE PERSONNES | C92: Ferroviaire | D92: Train en Espagne | E92: 0.0514 | F92: kgCO2e/passager.km | G92: 0.2 | H92: 42085 | I92: 43070 | J92: Base Empreinte ADEME
B93: DEPLACEMENT DE PERSONNES | C93: Ferroviaire | D93: Train en Italie | E93: 0.0317 | F93: kgCO2e/passager.km | G93: 0.2 | H93: 42085 | I93: 43070 | J93: Base Empreinte ADEME
B94: DEPLACEMENT DE PERSONNES | C94: Ferroviaire | D94: Train au Luxembourg | E94: 0.0397 | F94: kgCO2e/passager.km | G94: 0.2 | H94: 42085 | I94: 43070 | J94: Base Empreinte ADEME
B95: DEPLACEMENT DE PERSONNES | C95: Ferroviaire | D95: Train au Royaume Uni | E95: 0.075 | F95: kgCO2e/passager.km | G95: 0.2 | H95: 42085 | I95: 43070 | J95: Base Empreinte ADEME
B96: DEPLACEMENT DE PERSONNES | C96: Ferroviaire | D96: Train en Suisse | E96: 0.00374 | F96: kgCO2e/passager.km | G96: 0.2 | H96: 42085 | I96: 43070 | J96: Base Empreinte ADEME
B97: DEPLACEMENT DE PERSONNES | C97: Ferroviaire | D97: A COMPLETER DANS FACTEURS D'EMISSIONS
B98: DEPLACEMENT DE PERSONNES | C98: Ferroviaire | D98: A COMPLETER DANS FACTEURS D'EMISSIONS
B99: DEPLACEMENT DE PERSONNES | C99: Ferroviaire | D99: A COMPLETER DANS FACTEURS D'EMISSIONS
B100: DEPLACEMENT DE PERSONNES | C100: Ferroviaire | D100: A COMPLETER DANS FACTEURS D'EMISSIONS
...

Sheet Campus site 1
C3: EMISSIONS DU SITE CAMPUS 1
C4: Outil développé sur la base de la méthode Bilan Carbone® par AVENIR CLIMATIQUE
C5: SOURCES FIXES | D5: FRET | E5: DEPLACEMENTS DE PERSONNES | F5: CONSOMMABLES ET MATERIAUX | G5: RESTAURANT UNIVERSITAIRE | H5: DECHETS DIRECTS | I5: IMMOBILISATIONS | J5: TOTAL
C7: ATTENTION : lorsque vous entrez une valeur dans une des cases à fond orange, le maintien d'une valeur nulle (0) dans une des cases à fond blanc et police noire ne signifie pas que le résultat est nul, mais simplement que l'arrondi est nul.
C9: SOURCES FIXES
E13: COMBUSTIBLES FOSSILES
C15: Quelles sont les consommations de combustibles fossiles du campus quel qu'en soit l'usage ? | G15: Emissions de CO2 | I15: Incertitude | M15: Objectif de réduction | P15: Action de réduction
C16: Combustible | D16: Consommation (kWh PCI) | E16: kgCO2e/kWh PCI avec amont | G16: kgCO2e | I16: Fact. d'émission (%) | J16: Données (%) | K16: kgCO2e | M16: Objectif (%) | N16: kgCO2e | P16: Action de réduction planifiée :
C17: Gaz Naturel | D17: 3456200 | E17: =_xlfn.IFNA(VLOOKUP($C17,'Facteurs d''émission'!$D$2:$I$340,2,FALSE),"Non présent dans la base") -> 0.24 | G17: =D17*E17 -> 829488 | I17: =_xlfn.IFNA(VLOOKUP($C17,'Facteurs d''émission'!$D$2:$I$340,4,FALSE),"Non présent dans la base") -> 0.05 | K17: =G17*(1-(1-I17)*(1-J17)) -> 41474.4 | L17: =IF(D17*COUNTA(J17)>0,"ok","") | N17: =G17*M17 -> 0 | P17: * * *
C18: Fioul lourd | E18: =_xlfn.IFNA(VLOOKUP($C18,'Facteurs d''émission'!$D$2:$I$340,2,FALSE),"Non renseigné") -> 0.32 | G18: =D18*E18 -> 0 | I18: =_xlfn.IFNA(VLOOKUP($C18,'Facteurs d''émission'!$D$2:$I$340,4,FALSE),"Non présent dans la base") -> 0.05 | K18: =G18*(1-(1-I18)*(1-J18)) -> 0 | L18: =IF(D18*COUNTA(J18)>0,"ok","") | N18: =G18*M18 -> 0
C19: Fioul domestique | E19: =_xlfn.IFNA(VLOOKUP($C19,'Facteurs d''émission'!$D$2:$I$340,2,FALSE),"Non renseigné") -> 0.32 | G19: =D19*E19 -> 0 | I19: =_xlfn.IFNA(VLOOKUP($C19,'Facteurs d''émission'!$D$2:$I$340,4,FALSE),"Non présent dans la base") -> 0.05 | K19: =G19*(1-(1-I19)*(1-J19)) -> 0 | L19: =IF(D19*COUNTA(J19)>0,"ok","") | N19: =G19*M19 -> 0
C20: Bois granulé / Combustion en chaudière / Label E+ | E20: =_xlfn.IFNA(VLOOKUP($C20,'Facteurs d''émission'!$D$2:$I$340,2,FALSE),"Non renseigné") -> 0.027 | G20: =D20*E20 -> 0 | I20: =_xlfn.IFNA(VLOOKUP($C20,'Facteurs d''émission'!$D$2:$I$340,4,FALSE),"Non présent dans la base") -> 0 | K20: =G20*(1-(1-I20)*(1-J20)) -> 0 | L20: =IF(D20*COUNTA(J20)>0,"ok","") | N20: =G20*M20 -> 0
C21: A COMPLETER DANS FACTEURS D'EMISSIONS | E21: =_xlfn.IFNA(VLOOKUP($C21,'Facteurs d''émission'!$D$2:$I$340,2,FALSE),"Non renseigné") -> 0 | G21: =D21*E21 -> 0 | I21: =_xlfn.IFNA(VLOOKUP($C21,'Facteurs d''émission'!$D$2:$I$340,4,FALSE),"Non présent dans la base") -> 0 | K21: =G21*(1-(1-I21)*(1-J21)) -> 0 | L21: =IF(D21*COUNTA(J21)>0,"ok","") | N21: =G21*M21 -> 0
C22: A COMPLETER DANS FACTEURS D'EMISSIONS | E22: =_xlfn.IFNA(VLOOKUP($C22,'Facteurs d''émission'!$D$2:$I$340,2,FALSE),"Non renseigné") -> 0 | G22: =D22*E22 -> 0 | I22: =_xlfn.IFNA(VLOOKUP($C22,'Facteurs d''émission'!$D$2:$I$340,4,FALSE),"Non présent dans la base") -> 0 | K22: =G22*(1-(1-I22)*(1-J22)) -> 0 | L22: =IF(D22*COUNTA(J22)>0,"ok","") | N22: =G22*M22 -> 0
C23: A COMPLETER DANS FACTEURS D'EMISSIONS | E23: =_xlfn.IFNA(VLOOKUP($C23,'Facteurs d''émission'!$D$2:$I$340,2,FALSE),"Non renseigné") -> 0 | G23: =D23*E23 -> 0 | I23: =_xlfn.IFNA(VLOOKUP($C23,'Facteurs d''émission'!$D$2:$I$340,4,FALSE),"Non présent dans la base") -> 0 | K23: =G23*(1-(1-I23)*(1-J23)) -> 0 | L23: =IF(D23*COUNTA(J23)>0,"ok","") | N23: =G23*M23 -> 0
C24: Total | D24: =SUM(D17:D23) -> 3456200 | G24: =SUM(G17:G23) -> 829488 | I24: =IF(COUNTA(D17:D23)>COUNTIF(L17:L23,"ok"),"! Remplir une incertitude !","") -> ! Remplir une incertitude ! | K24: =SUM(K17:K23) -> 41474.4 | N24: =SUM(N17:N23) -> 0 | P24: =IF(N24>0,IF(#REF!="","Attention: vous devez planifier une action afin de remplir votre objectif",""),"")
E28: ELECTRICITE
C30: Quelle est la consommation totale en électricité du campus ? | G30: Emissions de CO2 | I30: Incertitude | M30: Objectif de réduction | P30: Action de réduction
C31: Source | D31: Consommation (kWh) | E31: kgCO2e par kWh | F31: Taux de pertes en ligne | G31: kgCO2e | I31: Fact. d'émission (%) | J31: Données (%) | K31: kgCO2e | M31: Objectif (%) | N31: kgCO2e | P31: Action de réduction planifiée :
C32: Mix électrique français (année 2024) | D32: 2091000 | E32: =_xlfn.IFNA(VLOOKUP($C32,'Facteurs d''émission'!$D$2:$I$340,2,FALSE),"Non renseigné") -> 0.0519 | F32: 0.1 | G32: =D32*E32*(1+F32) -> 119375.19 | I32: =_xlfn.IFNA(VLOOKUP($C32,'Facteurs d''émission'!$D$2:$I$340,4,FALSE),"Non présent dans la base") -> 0.1 | K32: =G32*(1-(1-I32)*(1-J32)) -> 11937.519 | L32: =IF(D32*COUNTA(J32)>0,"ok","") | N32: =G32*M32 -> 0 | P32: * * *
C33: A COMPLETER DANS FACTEURS D'EMISSIONS | E33: =_xlfn.IFNA(VLOOKUP($C33,'Facteurs d''émission'!$D$2:$I$340,2,FALSE),"Non renseigné") -> 0 | G33: =D33*E33*(1+F33) -> 0 | I33: =_xlfn.IFNA(VLOOKUP($C33,'Facteurs d''émission'!$D$2:$I$340,4,FALSE),"Non présent dans la base") -> 0 | K33: =G33*(1-(1-I33)*(1-J33)) -> 0 | L33: =IF(D33*COUNTA(J33)>0,"ok","") | N33: =G33*M33 -> 0
C34: A COMPLETER DANS FACTEURS D'EMISSIONS | E34: =_xlfn.IFNA(VLOOKUP($C34,'Facteurs d''émission'!$D$2:$I$340,2,FALSE),"Non renseigné") -> 0 | G34: =D34*E34*(1+F34) -> 0 | I34: =_xlfn.IFNA(VLOOKUP($C34,'Facteurs d''émission'!$D$2:$I$340,4,FALSE),"Non présent dans la base") -> 0 | K34: =G34*(1-(1-I34)*(1-J34)) -> 0 | L34: =IF(D34*COUNTA(J34)>0,"ok","") | N34: =G34*M34 -> 0
C35: A COMPLETER DANS FACTEURS D'EMISSIONS | E35: =_xlfn.IFNA(VLOOKUP($C35,'Facteurs d''émission'!$D$2:$I$340,2,FALSE),"Non renseigné") -> 0 | G35: =D35*E35*(1+F35) -> 0 | I35: =_xlfn.IFNA(VLOOKUP($C35,'Facteurs d''émission'!$D$2:$I$340,4,FALSE),"Non présent dans la base") -> 0 | K35: =G35*(1-(1-I35)*(1-J35)) -> 0 | L35: =IF(D35*COUNTA(J35)>0,"ok","") | N35: =G35*M35 -> 0
C36: Total | D36: =SUM(D32:D35) -> 2091000 | G36: =SUM(G32:G35) -> 119375.19 | I36: =IF(COUNTA(D32:D35)>COUNTIF(L32:L35,"ok"),"! Remplir une incertitude !","") -> ! Remplir une incertitude ! | K36: =SUM(K32:K35) -> 11937.519 | N36: =SUM(N32:N35) -> 0 | P36: =IF(N36>0,IF(#REF!="","Attention: vous devez planifier une action afin de remplir votre objectif",""),"")
E40: FUITES DE FLUIDES FRIGORIGENES (Climatisation)
C42: Quelles sont les émissions liées aux fuites de gaz frigorigènes (climatisation, chambres froides, etc.) ? | G42: Emissions de CO2 | I42: Incertitude | M42: Objectif de réduction | P42: Action de réduction
C43: Nature du gaz utilisé | D43: kg émis par an | E43: kgCO2e par kg | G43: kgCO2e | I43: Fact. d'émission (%) | J43: Données (%) | K43: kgCO2e | M43: Objectif (%) | N43: kgCO2e | P43: Action de réduction planifiée :
C44: R134a | E44: =_xlfn.IFNA(VLOOKUP($C44,'Facteurs d''émission'!$D$2:$I$340,2,FALSE),"Non renseigné") -> 1530 | G44: =D44*E44 -> 0 | I44: =_xlfn.IFNA(VLOOKUP($C44,'Facteurs d''émission'!$D$2:$I$340,4,FALSE),"Non présent dans la base") -> 0.3 | K44: =G44*(1-(1-I44)*(1-J44)) -> 0 | L44: =IF(D44*COUNTA(J44)>0,"ok","") | N44: =G44*M44 -> 0 | P44: * * *
C45: R407c | E45: =_xlfn.IFNA(VLOOKUP($C45,'Facteurs d''émission'!$D$2:$I$340,2,FALSE),"Non renseigné") -> 1910 | G45: =D45*E45 -> 0 | I45: =_xlfn.IFNA(VLOOKUP($C45,'Facteurs d''émission'!$D$2:$I$340,4,FALSE),"Non présent dans la base") -> 0.3 | K45: =G45*(1-(1-I45)*(1-J45)) -> 0 | L45: =IF(D45*COUNTA(J45)>0,"ok","") | N45: =G45*M45 -> 0
C46: R32 | E46: =_xlfn.IFNA(VLOOKUP($C46,'Facteurs d''émission'!$D$2:$I$340,2,FALSE),"Non renseigné") -> 770 | G46: =D46*E46 -> 0 | I46: =_xlfn.IFNA(VLOOKUP($C46,'Facteurs d''émission'!$D$2:$I$340,4,FALSE),"Non présent dans la base") -> 0.3 | K46: =G46*(1-(1-I46)*(1-J46)) -> 0 | L46: =IF(D46*COUNTA(J46)>0,"ok","") | N46: =G46*M46 -> 0
C47: R410a | D47: 135 | E47: =_xlfn.IFNA(VLOOKUP($C47,'Facteurs d''émission'!$D$2:$I$340,2,FALSE),"Non renseigné") -> 2260 | G47: =D47*E47 -> 305100 | I47: =_xlfn.IFNA(VLOOKUP($C47,'Facteurs d''émission'!$D$2:$I$340,4,FALSE),"Non présent dans la base") -> 0.3 | K47: =G47*(1-(1-I47)*(1-J47)) -> 91530 | L47: =IF(D47*COUNTA(J47)>0,"ok","") | N47: =G47*M47 -> 0
C48: A COMPLETER DANS FACTEURS D'EMISSIONS | E48: =_xlfn.IFNA(VLOOKUP($C48,'Facteurs d''émission'!$D$2:$I$340,2,FALSE),"Non renseigné") -> 0 | G48: =D48*E48 -> 0 | I48: =_xlfn.IFNA(VLOOKUP($C48,'Facteurs d''émission'!$D$2:$I$340,4,FALSE),"Non présent dans la base") -> 0 | K48: =G48*(1-(1-I48)*(1-J48)) -> 0 | L48: =IF(D48*COUNTA(J48)>0,"ok","") | N48: =G48*M48 -> 0
C49: A COMPLETER DANS FACTEURS D'EMISSIONS | E49: =_xlfn.IFNA(VLOOKUP($C49,'Facteurs d''émission'!$D$2:$I$340,2,FALSE),"Non renseigné") -> 0 | G49: =D49*E49 -> 0 | I49: =_xlfn.IFNA(VLOOKUP($C49,'Facteurs d''émission'!$D$2:$I$340,4,FALSE),"Non présent dans la base") -> 0 | K49: =G49*(1-(1-I49)*(1-J49)) -> 0 | L49: =IF(D49*COUNTA(J49)>0,"ok","") | N49: =G49*M49 -> 0
C50: Total | D50: =SUM(D44:D49) -> 135 | G50: =SUM(G44:G49) -> 305100 | I50: =IF(COUNTA(D44:D49)>COUNTIF(L44:L49,"ok"),"! Remplir une incertitude !","") -> ! Remplir une incertitude ! | K50: =SUM(K44:K49) -> 91530 | N50: =SUM(N44:N49) -> 0 | P50: =IF(N50>0,IF(#REF!="","Attention: vous devez planifier une action afin de remplir votre objectif",""),"")
C54: RESULTATS DES SOURCES FIXES
C56: RECAPITULATIF EQUIVALENT CARBONE | E56: Emissions | I56: Incertitude | M56: Objectif de réduction | P56: Résiduel
C57: SOURCES FIXES, Equivalent Carbone | E57: kgCO2e | F57: tCO2e | G57: en % du total | I57: kgCO2e | J57: tCO2e | K57: % | M57: kgCO2e | N57: tCO2e | O57: en % | P57: tCO2e
C58: Combustibles fossiles | E58: =G24 -> 829488 | F58: =E58/1000 -> 829.488 | G58: =IF(F$61=0,"",F58/F$61) -> 0.6614931 | I58: =K24 -> 41474.4 | J58: =I58/1000 -> 41.4744 | K58: =IF(E58=0,"",I58/E58) -> 0.05 | M58: =N24 -> 0 | N58: =M58/1000 -> 0 | O58: =IF($E58=0,"",M58/$E58) -> 0 | P58: =F58-N58 -> 829.488
C59: Electricité | E59: =G36 -> 119375.19 | F59: =E59/1000 -> 119.37519 | G59: =IF(F$61=0,"",F59/F$61) -> 0.095198321 | I59: =K36 -> 11937.519 | J59: =I59/1000 -> 11.937519 | K59: =IF(E59=0,"",I59/E59) -> 0.1 | M59: =N36 -> 0 | N59: =M59/1000 -> 0 | O59: =IF($E59=0,"",M59/$E59) -> 0 | P59: =F59-N59 -> 119.37519
C60: Fuites de fluides frigorigènes | E60: =G50 -> 305100 | F60: =E60/1000 -> 305.1 | G60: =IF(F$61=0,"",F60/F$61) -> 0.24330858 | I60: =K50 -> 91530 | J60: =I60/1000 -> 91.53 | K60: =IF(E60=0,"",I60/E60) -> 0.3 | M60: =N50 -> 0 | N60: =M60/1000 -> 0 | O60: =IF($E60=0,"",M60/$E60) -> 0 | P60: =F60-N60 -> 305.1
C61: TOTAL | E61: =SUM(E58:E60) -> 1253963.2 | F61: =SUM(F58:F60) -> 1253.9632 | G61: =SUM(G58:G60) -> 1 | I61: =SUM(I58:I60) -> 144941.92 | J61: =SUM(J58:J60) -> 144.94192 | K61: =IF(E61=0,"",I61/E61) -> 0.11558706 | M61: =SUM(M58:M60) -> 0 | N61: =SUM(N58:N60) -> 0 | O61: =IF($E61=0,"",M61/$E61) -> 0 | P61: =SUM(P58:P60) -> 1253.9632
C103: FRET
E106: FRET ROUTIER
C109: Quelle est la somme des tonnes de marchandise transportées par km sur le fret routier pour chaque type de véhicule et livrées pour le campus ? | G109: Emissions de CO2 | I109: Incertitude | M109: Objectif de réduction | P109: Action de réduction
C110: Type de véhicule | D110: Nb de tonne.km | E110: Fabrication + carburant kgCO2e par tonne.km avec amont | G110: kgCO2e | I110: Fact. d'émission (%) | J110: Données (%) | K110: kgCO2e | M110: Objectif (%) | N110: kgCO2e | P110: Action de réduction planifiée :
P111: * * * * *
C113: Véhicule Utilitaire Léger - Essence | D113: 35600 | E113: =_xlfn.IFNA(VLOOKUP($C113,'Facteurs d''émission'!$D$2:$I$340,2,FALSE),"Non renseigné") -> 0.92 | G113: =D113*E113 -> 32752 | I113: =_xlfn.IFNA(VLOOKUP($C113,'Facteurs d''émission'!$D$2:$I$340,4,FALSE),"Non présent dans la base") -> 0.7 | K113: =G113*(1-(1-I113)*(1-J113)) -> 22926.4 | L113: =IF(D113*COUNTA(J113)>0,"ok","") | N113: =G113*M113 -> 0
C114: Camion porteur - Diesel avec 7% biodiesel, PTAC 20T | E114: =_xlfn.IFNA(VLOOKUP($C114,'Facteurs d''émission'!$D$2:$I$340,2,FALSE),"Non renseigné") -> 0.17 | G114: =D114*E114 -> 0 | I114: =_xlfn.IFNA(VLOOKUP($C114,'Facteurs d''émission'!$D$2:$I$340,4,FALSE),"Non présent dans la base") -> 0.7 | K114: =G114*(1-(1-I114)*(1-J114)) -> 0 | L114: =IF(D114*COUNTA(J114)>0,"ok","") | N114: =G114*M114 -> 0
C115: Camion porteur - Diesel avec 7% biodiesel, PTRA 40T | E115: =_xlfn.IFNA(VLOOKUP($C115,'Facteurs d''émission'!$D$2:$I$340,2,FALSE),"Non renseigné") -> 0.087 | G115: =D115*E115 -> 0 | I115: =_xlfn.IFNA(VLOOKUP($C115,'Facteurs d''émission'!$D$2:$I$340,4,FALSE),"Non présent dans la base") -> 0.7 | K115: =G115*(1-(1-I115)*(1-J115)) -> 0 | L115: =IF(D115*COUNTA(J115)>0,"ok","") | N115: =G115*M115 -> 0
C116: Camion porteur - Diesel avec 7% biodiesel, PTRA 26T | E116: =_xlfn.IFNA(VLOOKUP($C116,'Facteurs d''émission'!$D$2:$I$340,2,FALSE),"Non renseigné") -> 0.14 | G116: =D116*E116 -> 0 | I116: =_xlfn.IFNA(VLOOKUP($C116,'Facteurs d''émission'!$D$2:$I$340,4,FALSE),"Non présent dans la base") -> 0.7 | K116: =G116*(1-(1-I116)*(1-J116)) -> 0 | L116: =IF(D116*COUNTA(J116)>0,"ok","") | N116: =G116*M116 -> 0
C117: Camion porteur - Diesel avec 7% biodiesel, PTAC 7,5T | E117: =_xlfn.IFNA(VLOOKUP($C117,'Facteurs d''émission'!$D$2:$I$340,2,FALSE),"Non renseigné") -> 0.4 | G117: =D117*E117 -> 0 | I117: =_xlfn.IFNA(VLOOKUP($C117,'Facteurs d''émission'!$D$2:$I$340,4,FALSE),"Non présent dans la base") -> 0.7 | K117: =G117*(1-(1-I117)*(1-J117)) -> 0 | L117: =IF(D117*COUNTA(J117)>0,"ok","") | N117: =G117*M117 -> 0
C118: A COMPLETER DANS FACTEURS D'EMISSIONS | E118: =_xlfn.IFNA(VLOOKUP($C118,'Facteurs d''émission'!$D$2:$I$340,2,FALSE),"Non renseigné") -> 0 | G118: =D118*E118 -> 0 | I118: =_xlfn.IFNA(VLOOKUP($C118,'Facteurs d''émission'!$D$2:$I$340,4,FALSE),"Non présent dans la base") -> 0 | K118: =G118*(1-(1-I118)*(1-J118)) -> 0 | N118: =G118*M118 -> 0
C119: A COMPLETER DANS FACTEURS D'EMISSIONS | E119: =_xlfn.IFNA(VLOOKUP($C119,'Facteurs d''émission'!$D$2:$I$340,2,FALSE),"Non renseigné") -> 0 | G119: =D119*E119 -> 0 | I119: =_xlfn.IFNA(VLOOKUP($C119,'Facteurs d''émission'!$D$2:$I$340,4,FALSE),"Non présent dans la base") -> 0 | K119: =G119*(1-(1-I119)*(1-J119)) -> 0 | N119: =G119*M119 -> 0
C120: A COMPLETER DANS FACTEURS D'EMISSIONS | E120: =_xlfn.IFNA(VLOOKUP($C120,'Facteurs d''émission'!$D$2:$I$340,2,FALSE),"Non renseigné") -> 0 | G120: =D120*E120 -> 0 | I120: =_xlfn.IFNA(VLOOKUP($C120,'Facteurs d''émission'!$D$2:$I$340,4,FALSE),"Non présent dans la base") -> 0 | K120: =G120*(1-(1-I120)*(1-J120)) -> 0 | N120: =G120*M120 -> 0
C121: Total | D121: =SUM(D113:D120) -> 35600 | G121: =SUM(G113:G120) -> 32752 | I121: =IF(COUNTA(D113:D120)>COUNTIF(L113:L120,"ok"),"! Remplir une incertitude !","") -> ! Remplir une incertitude ! | K121: =SUM(K113:K120) -> 22926.4 | N121: =SUM(N113:N120) -> 0 | P121: =IF(N121>0,IF(P111="","Attention: vous devez planifier une action afin de remplir votre objectif",""),"")
E123: FRET AERIEN
C125: Quelle est la somme des tonnes de marchandise transportées par km sur le fret aérien pour chaque type de courrier et livrées pour le campus ? | G125: Emissions de CO2 | I125: Incertitude | M125: Objectif de réduction | P125: Action de réduction
C126: Type de courrier | D126: Nb de tonnes.km | E126: CO2 seul kgCO2e/tonne.km avec amont | F126: Forcage radiatif kgCO2e par tonne.km | G126: kgCO2e | I126: Fact. d'émission (%) | J126: Données (%) | K126: kgCO2e | M126: Objectif (%) | N126: kgCO2e | P126: Action de réduction planifiée :
C127: Avion (marchandises) - plus de 220 sièges, trajet de 1000 - 2000 km avec trainées | E127: =_xlfn.IFNA(VLOOKUP($C127,'Facteurs d''émission'!$D$2:$I$340,2,FALSE),"Non renseigné") -> 2.36 | G127: =D127*(E127+F127) -> 0 | I127: =_xlfn.IFNA(VLOOKUP($C127,'Facteurs d''émission'!$D$2:$I$340,4,FALSE),"Non présent dans la base") -> 0.7 | K127: =G127*(1-(1-I127)*(1-J127)) -> 0 | L127: =IF(D127*COUNTA(J127)>0,"ok","") | N127: =M127*G127 -> 0 | P127: * * * * *
C128: Avion (marchandises) - plus de 220 sièges, trajet de 2000 - 5000 km | E128: =_xlfn.IFNA(VLOOKUP($C128,'Facteurs d''émission'!$D$2:$I$340,2,FALSE),"Non renseigné") -> 1.69 | G128: =D128*(E128+F128) -> 0 | I128: =_xlfn.IFNA(VLOOKUP($C128,'Facteurs d''émission'!$D$2:$I$340,4,FALSE),"Non présent dans la base") -> 0.7 | K128: =G128*(1-(1-I128)*(1-J128)) -> 0 | L128: =IF(D128*COUNTA(J128)>0,"ok","") | N128: =M128*G128 -> 0
C129: Avion (marchandises) - plus de 220 sièges, trajet > 5000 km | E129: =_xlfn.IFNA(VLOOKUP($C129,'Facteurs d''émission'!$D$2:$I$340,2,FALSE),"Non renseigné") -> 1.51 | G129: =D129*(E129+F129) -> 0 | I129: =_xlfn.IFNA(VLOOKUP($C129,'Facteurs d''émission'!$D$2:$I$340,4,FALSE),"Non présent dans la base") -> 0.7 | K129: =G129*(1-(1-I129)*(1-J129)) -> 0 | L129: =IF(D129*COUNTA(J129)>0,"ok","") | N129: =M129*G129 -> 0
C130: A COMPLETER DANS FACTEURS D'EMISSIONS | E130: =_xlfn.IFNA(VLOOKUP($C130,'Facteurs d''émission'!$D$2:$I$340,2,FALSE),"Non renseigné") -> 0 | G130: =D130*(E130+F130) -> 0 | I130: =_xlfn.IFNA(VLOOKUP($C130,'Facteurs d''émission'!$D$2:$I$340,4,FALSE),"Non présent dans la base") -> 0 | K130: =G130*(1-(1-I130)*(1-J130)) -> 0 | N130: =M130*G130 -> 0
C131: A COMPLETER DANS FACTEURS D'EMISSIONS | E131: =_xlfn.IFNA(VLOOKUP($C131,'Facteurs d''émission'!$D$2:$I$340,2,FALSE),"Non renseigné") -> 0 | G131: =D131*(E131+F131) -> 0 | I131: =_xlfn.IFNA(VLOOKUP($C131,'Facteurs d''émission'!$D$2:$I$340,4,FALSE),"Non présent dans la base") -> 0 | K131: =G131*(1-(1-I131)*(1-J131)) -> 0 | N131: =M131*G131 -> 0
C132: A COMPLETER DANS FACTEURS D'EMISSIONS | E132: =_xlfn.IFNA(VLOOKUP($C132,'Facteurs d''émission'!$D$2:$I$340,2,FALSE),"Non renseigné") -> 0 | G132: =D132*(E132+F132) -> 0 | I132: =_xlfn.IFNA(VLOOKUP($C132,'Facteurs d''émission'!$D$2:$I$340,4,FALSE),"Non présent dans la base") -> 0 | K132: =G132*(1-(1-I132)*(1-J132)) -> 0 | N132: =M132*G132 -> 0
C133: Total | D133: =SUM(D127:D132) -> 0 | G133: =SUM(G127:G132) -> 0 | I133: =IF(COUNTA(D127:D129)>COUNTIF(L127:L129,"ok"),"! Remplir une incertitude !","") | K133: =SUM(K127:K132) -> 0 | N133: =SUM(N127:N132) -> 0 | P133: =IF(N133>0,IF(#REF!="","Attention: vous devez planifier une action afin de remplir votre objectif",""),"")
E135: FRET FERROVIAIRE
C137: Quelle est la somme des tonnes de marchandise transportées par km sur le fret ferroviaire et livrées pour le campus ? | G137: Emissions de CO2 | I137: Incertitude | M137: Objectif de réduction | P137: Action de réduction
C138: Type de fret ferroviaire | D138: Nb de tonnes.km | E138: kgCO2e par tonne.km | G138: kgCO2e | I138: Fact. d'émission (%) | J138: Données (%) | K138: kgCO2e | M138: Objectif (%) | N138: kgCO2e | P138: Action de réduction planifiée :
C139: Train de marchandises (Europe) - Gazole | E139: =_xlfn.IFNA(VLOOKUP($C139,'Facteurs d''émission'!$D$2:$I$340,2,FALSE),"Non renseigné") -> 0.0613 | G139: =D139*E139 -> 0 | I139: =_xlfn.IFNA(VLOOKUP($C139,'Facteurs d''émission'!$D$2:$I$340,4,FALSE),"Non présent dans la base") -> 0 | K139: =G139*(1-(1-I139)*(1-J139)) -> 0 | L139: =IF(D139*COUNTA(J139)>0,"ok","") | N139: =M139*G139 -> 0 | P139: * * * * *
C140: Train de marchandises (France) - motorisation électrique, chargement dense | E140: =_xlfn.IFNA(VLOOKUP($C140,'Facteurs d''émission'!$D$2:$I$340,2,FALSE),"Non renseigné") -> 0.00404 | G140: =D140*E140 -> 0 | I140: =_xlfn.IFNA(VLOOKUP($C140,'Facteurs d''émission'!$D$2:$I$340,4,FALSE),"Non présent dans la base") -> 0.7 | K140: =G140*(1-(1-I140)*(1-J140)) -> 0 | L140: =IF(D140*COUNTA(J140)>0,"ok","") | N140: =M140*G140 -> 0
C141: A COMPLETER DANS FACTEURS D'EMISSIONS | E141: =_xlfn.IFNA(VLOOKUP($C141,'Facteurs d''émission'!$D$2:$I$340,2,FALSE),"Non renseigné") -> 0 | G141: =D141*E141 -> 0 | I141: =_xlfn.IFNA(VLOOKUP($C141,'Facteurs d''émission'!$D$2:$I$340,4,FALSE),"Non présent dans la base") -> 0 | K141: =G141*(1-(1-I141)*(1-J141)) -> 0 | N141: =M141*G141 -> 0
C142: A COMPLETER DANS FACTEURS D'EMISSIONS | E142: =_xlfn.IFNA(VLOOKUP($C142,'Facteurs d''émission'!$D$2:$I$340,2,FALSE),"Non renseigné") -> 0 | G142: =D142*E142 -> 0 | I142: =_xlfn.IFNA(VLOOKUP($C142,'Facteurs d''émission'!$D$2:$I$340,4,FALSE),"Non présent dans la base") -> 0 | K142: =G142*(1-(1-I142)*(1-J142)) -> 0 | N142: =M142*G142 -> 0
C143: A COMPLETER DANS FACTEURS D'EMISSIONS | E143: =_xlfn.IFNA(VLOOKUP($C143,'Facteurs d''émission'!$D$2:$I$340,2,FALSE),"Non renseigné") -> 0 | G143: =D143*E143 -> 0 | I143: =_xlfn.IFNA(VLOOKUP($C143,'Facteurs d''émission'!$D$2:$I$340,4,FALSE),"Non présent dans la base") -> 0 | K143: =G143*(1-(1-I143)*(1-J143)) -> 0 | N143: =M143*G143 -> 0
C144: Total | D144: =SUM(D139:D143) -> 0 | G144: =SUM(G139:G143) -> 0 | I144: =IF(COUNTA(D139:D140)>COUNTIF(L139:L140,"ok"),"! Remplir une incertitude !","") | K144: =SUM(K139:K143) -> 0 | N144: =SUM(N139:N143) -> 0 | P144: =IF(N144>0,IF(#REF!="","Attention: vous devez planifier une action afin de remplir votre objectif",""),"")
E146: FRET FLUVIAL / MARITIME
C148: Quelle est la somme des tonnes de marchandise transportées par km sur le fret maritime et livrées pour le campus ? | G148: Emissions de CO2 | I148: Incertitude | M148: Objectif de réduction | P148: Action de réduction
C149: Type de fret maritime / fluvial | D149: Tonnes.km effectuées | E149: kgCO2e par tonne.km | G149: kgCO2e | I149: Fact. d'émission (%) | J149: Données (%) | K149: kgCO2e | M149: Objectif (%) | N149: kgCO2e | P149: Action de réduction planifiée :
C150: Porte-conteneurs (moyenne mondiale) | E150: =_xlfn.IFNA(VLOOKUP($C150,'Facteurs d''émission'!$D$2:$I$340,2,FALSE),"Non renseigné") -> 0.0102 | G150: =D150*E150 -> 0 | I150: =_xlfn.IFNA(VLOOKUP($C150,'Facteurs d''émission'!$D$2:$I$340,4,FALSE),"Non présent dans la base") -> 0 | K150: =G150*(1-(1-I150)*(1-J150)) -> 0 | N150: =$M150*G150 -> 0 | P150: * * * * *
C151: Porte-conteneurs frigorifique (moyenne mondiale) | E151: =_xlfn.IFNA(VLOOKUP($C151,'Facteurs d''émission'!$D$2:$I$340,2,FALSE),"Non renseigné") -> 0.0227 | G151: =D151*E151 -> 0 | I151: =_xlfn.IFNA(VLOOKUP($C151,'Facteurs d''émission'!$D$2:$I$340,4,FALSE),"Non présent dans la base") -> 0 | K151: =G151*(1-(1-I151)*(1-J151)) -> 0 | L151: =IF(D151*COUNTA(J151)>0,"ok","") | N151: =$M151*G151 -> 0
C152: A COMPLETER DANS FACTEURS D'EMISSIONS | E152: =_xlfn.IFNA(VLOOKUP($C152,'Facteurs d''émission'!$D$2:$I$340,2,FALSE),"Non renseigné") -> 0 | G152: =D152*E152 -> 0 | I152: =_xlfn.IFNA(VLOOKUP($C152,'Facteurs d''émission'!$D$2:$I$340,4,FALSE),"Non présent dans la base") -> 0 | K152: =G152*(1-(1-I152)*(1-J152)) -> 0 | N152: =$M152*G152 -> 0
C153: A COMPLETER DANS FACTEURS D'EMISSIONS | E153: =_xlfn.IFNA(VLOOKUP($C153,'Facteurs d''émission'!$D$2:$I$340,2,FALSE),"Non renseigné") -> 0 | G153: =D153*E153 -> 0 | I153: =_xlfn.IFNA(VLOOKUP($C153,'Facteurs d''émission'!$D$2:$I$340,4,FALSE),"Non présent dans la base") -> 0 | K153: =G153*(1-(1-I153)*(1-J153)) -> 0 | N153: =$M153*G153 -> 0
C154: A COMPLETER DANS FACTEURS D'EMISSIONS | E154: =_xlfn.IFNA(VLOOKUP($C154,'Facteurs d''émission'!$D$2:$I$340,2,FALSE),"Non renseigné") -> 0 | G154: =D154*E154 -> 0 | I154: =_xlfn.IFNA(VLOOKUP($C154,'Facteurs d''émission'!$D$2:$I$340,4,FALSE),"Non présent dans la base") -> 0 | K154: =G154*(1-(1-I154)*(1-J154)) -> 0 | N154: =$M154*G154 -> 0
C155: A COMPLETER DANS FACTEURS D'EMISSIONS | E155: =_xlfn.IFNA(VLOOKUP($C155,'Facteurs d''émission'!$D$2:$I$340,2,FALSE),"Non renseigné") -> 0 | G155: =D155*E155 -> 0 | I155: =_xlfn.IFNA(VLOOKUP($C155,'Facteurs d''émission'!$D$2:$I$340,4,FALSE),"Non présent dans la base") -> 0 | K155: =G155*(1-(1-I155)*(1-J155)) -> 0 | N155: =$M155*G155 -> 0
C156: Total | D156: =SUM(D150:D155) -> 0 | G156: =SUM(G150:G155) -> 0 | I156: =IF(COUNTA(D151)>COUNTIF(L151,"ok"),"! Remplir une incertitude !","") | K156: =SUM(K150:K155) -> 0 | N156: =SUM(N150:N155) -> 0 | P156: =IF(N156>0,IF(#REF!="","Attention: vous devez planifier une action afin de remplir votre objectif",""),"")
C160: RESULTATS FRET
C162: RECAPITULATIF EQUIVALENT CARBONE | E162: Emissions | I162: Incertitude | M162: Objectif de réduction | P162: Résiduel
E163: kgCO2e | F163: tCO2e | G163: en % du total | I163: kgCO2e | J163: tCO2e | K163: % | M163: kgCO2e | N163: tCO2e | O163: en % | P163: tCO2e
C164: Fret routier | E164: =G121 -> 32752 | F164: =E164/1000 -> 32.752 | G164: =IF(F$168=0,"",F164/F$168) -> 1 | I164: =K121 -> 22926.4 | J164: =I164/1000 -> 22.9264 | K164: =IF(E164=0,"",I164/E164) -> 0.7 | M164: =N121 -> 0 | N164: =M164/1000 -> 0 | O164: =IF($E164=0,"",M164/$E164) -> 0 | P164: =F164-N164 -> 32.752
C165: Fret aérien | E165: =G133 -> 0 | F165: =E165/1000 -> 0 | G165: =IF(F$168=0,"",F165/F$168) -> 0 | I165: =K133 -> 0 | J165: =I165/1000 -> 0 | K165: =IF(E165=0,"",I165/E165) | M165: =N133 -> 0 | N165: =M165/1000 -> 0 | O165: =IF($E165=0,"",M165/$E165) | P165: =F165-N165 -> 0
C166: Fret ferroviaire | E166: =G144 -> 0 | F166: =E166/1000 -> 0 | G166: =IF(F$168=0,"",F166/F$168) -> 0 | I166: =K144 -> 0 | J166: =I166/1000 -> 0 | K166: =IF(E166=0,"",I166/E166) | M166: =N144 -> 0 | N166: =M166/1000 -> 0 | O166: =IF($E166=0,"",M166/$E166) | P166: =F166-N166 -> 0
C167: Fret maritime | E167: =G156 -> 0 | F167: =E167/1000 -> 0 | G167: =IF(F$168=0,"",F167/F$168) -> 0 | I167: =K156 -> 0 | J167: =I167/1000 -> 0 | K167: =IF(E167=0,"",I167/E167) | M167: =N156 -> 0 | N167: =M167/1000 -> 0 | O167: =IF($E167=0,"",M167/$E167) | P167: =F167-N167 -> 0
C168: TOTAL | E168: =SUM(E164:E167) -> 32752 | F168: =SUM(F164:F167) -> 32.752 | G168: =SUM(G164:G167) -> 1 | I168: =SUM(I164:I167) -> 22926.4 | J168: =SUM(J164:J167) -> 22.9264 | K168: =IF(E168=0,"",I168/E168) -> 0.7 | M168: =SUM(M164:M167) -> 0 | N168: =SUM(N164:N167) -> 0 | O168: =IF($E168=0,"",M168/$E168) -> 0 | P168: =SUM(P164:P167) -> 32.752
C208: DEPLACEMENTS DE PERSONNES
E210: AUTOMOBILE
C212: Quelle est la somme des km parcourus par type de trajet en voiture pour toutes les personnes accédant au campus ? | I212: Emissions de CO2 | N212: Incertitude | U212: Objectif de réduction | AA212: Action de réduction
C213: Type de parcours | D213: Kilomètres parcourus : | G213: kgCO2e par km parcouru | I213: kgCO2e | N213: Fact. d'émission (%) | O213: Données (%) | P213: kgCO2e | U213: Objectif (%) | V213: kgCO2e à long terme | AA213: Action de réduction planifiée :
D214: Domicile-travail | E214: Hors dom-travail | F214: Visiteurs | I214: Dom-Travail | J214: Hors dom-tr | K214: Visiteurs | L214: Total | P214: Dom-Travail | Q214: Hors dom-tr | R214: Visiteurs | S214: Total | V214: Dom-Travail | W214: Hors dom-tr | X214: Visiteurs | Y214: Total | AA214: * * * * * *
C215: Voiture particulière (moyenne; essence) | D215: =265320*1.25 -> 331650 | G215: =_xlfn.IFNA(VLOOKUP($C215,'Facteurs d''émission'!$D$2:$I$340,2,FALSE),"Non renseigné") -> 0.27 | I215: =IFERROR(D215*$G215,0) -> 89545.5 | J215: =IFERROR(E215*$G215,0) -> 0 | K215: =IFERROR(F215*$G215,0) -> 0 | L215: =SUM(I215:K215) -> 89545.5 | N215: =_xlfn.IFNA(VLOOKUP($C215,'Facteurs d''émission'!$D$2:$I$340,4,FALSE),"Non présent dans la base") -> 0.6 | P215: =I215*(1-(1-$N215)*(1-$O215)) -> 53727.3 | Q215: =J215*(1-(1-$N215)*(1-$O215)) -> 0 | R215: =K215*(1-(1-$N215)*(1-$O215)) -> 0 | S215: =SUM(P215:R215) -> 53727.3 | T215: =IF(COUNTA(D215:F215)*COUNTA(O215)>0,"ok","") | V215: =$U215*I215 -> 0 | W215: =$U215*J215 -> 0 | X215: =$U215*K215 -> 0 | Y215: =SUM(V215:X215) -> 0
C216: Voiture particulière (moyenne; diesel) | D216: =132660*1.25 -> 165825 | G216: =_xlfn.IFNA(VLOOKUP($C216,'Facteurs d''émission'!$D$2:$I$340,2,FALSE),"Non renseigné") -> 0.24 | I216: =IFERROR(D216*$G216,0) -> 39798 | J216: =IFERROR(E216*$G216,0) -> 0 | K216: =IFERROR(F216*$G216,0) -> 0 | L216: =SUM(I216:K216) -> 39798 | N216: =_xlfn.IFNA(VLOOKUP($C216,'Facteurs d''émission'!$D$2:$I$340,4,FALSE),"Non présent dans la base") -> 0.6 | P216: =I216*(1-(1-$N216)*(1-$O216)) -> 23878.8 | Q216: =J216*(1-(1-$N216)*(1-$O216)) -> 0 | R216: =K216*(1-(1-$N216)*(1-$O216)) -> 0 | S216: =SUM(P216:R216) -> 23878.8 | T216: =IF(COUNTA(D216:F216)*COUNTA(O216)>0,"ok","") | V216: =$U216*I216 -> 0 | W216: =$U216*J216 -> 0 | X216: =$U216*K216 -> 0 | Y216: =SUM(V216:X216) -> 0
C217: A COMPLETER DANS FACTEURS D'EMISSIONS | G217: =_xlfn.IFNA(VLOOKUP($C217,'Facteurs d''émission'!$D$2:$I$340,2,FALSE),"Non renseigné") -> 0 | I217: =IFERROR(D217*$G217,0) -> 0 | J217: =IFERROR(E217*$G217,0) -> 0 | K217: =IFERROR(F217*$G217,0) -> 0 | L217: =SUM(I217:K217) -> 0 | N217: =_xlfn.IFNA(VLOOKUP($C217,'Facteurs d''émission'!$D$2:$I$340,4,FALSE),"Non présent dans la base") -> 0 | P217: =I217*(1-(1-$N217)*(1-$O217)) -> 0 | Q217: =J217*(1-(1-$N217)*(1-$O217)) -> 0 | R217: =K217*(1-(1-$N217)*(1-$O217)) -> 0 | S217: =SUM(P217:R217) -> 0 | T217: =IF(COUNTA(D217:F217)*COUNTA(O217)>0,"ok","") | V217: =$U217*I217 -> 0 | W217: =$U217*J217 -> 0 | X217: =$U217*K217 -> 0 | Y217: =SUM(V217:X217) -> 0
...

Sheet Totalisateur
B2: TOTALISATEUR
C4: SITE 1 | D4: SITE 2 | E4: SITE 3
C5: tCO2e | D5: tCO2e | E5: tCO2e
B6: SOURCES FIXES | C6: =SUM(C7:C9) -> 1253.9632 | E6: =SUM(E7:E9) -> 0 | G6: Total des émissions | K6: Total des incertitudes
B7: ='Campus site 1'!C58 -> Combustibles fossiles | C7: ='Campus site 1'!$E58/1000 -> 829.488 | G7: POSTES | H7: tCO2e | I7: % du total | K7: tCO2e | L7: % du total
B8: ='Campus site 1'!C59 -> Electricité | C8: ='Campus site 1'!$E59/1000 -> 119.37519 | G8: Sources fixes | H8: =SUM(C6:E6) -> 1253.9632 | I8: =IF($H$15=0,"",H8/$H$15) -> 0.47025012 | L8: =IFERROR(K8/H8,"") -> 0
B9: ='Campus site 1'!C60 -> Fuites de fluides frigorigènes | C9: ='Campus site 1'!$E60/1000 -> 305.1 | G9: Fret | H9: =SUM(C11:E11) -> 32.752 | I9: =IF($H$15=0,"",H9/$H$15) -> 0.012282364 | L9: =IFERROR(K9/H9,"") -> 0
G10: Déplacements de personnes | H10: =SUM(C17:E17) -> 490.43616 | I10: =IF($H$15=0,"",H10/$H$15) -> 0.18391901 | L10: =IFERROR(K10/H10,"") -> 0
B11: ='Campus site 1'!C103 -> FRET | C11: =SUM(C12:C15) -> 32.752 | E11: =SUM(E12:E15) -> 0 | G11: Consommables et matériaux | H11: =SUM(C23:E23) -> 28.703466 | I11: =IF($H$15=0,"",H11/$H$15) -> 0.010764118 | L11: =IFERROR(K11/H11,"") -> 0
B12: ='Campus site 1'!C164 -> Fret routier | C12: ='Campus site 1'!$F164 -> 32.752 | G12: Restaurant universitaire | H12: =SUM(C31:E31) -> 457.164 | I12: =IF($H$15=0,"",H12/$H$15) -> 0.17144158 | L12: =IFERROR(K12/H12,"") -> 0
B13: ='Campus site 1'!C165 -> Fret aérien | C13: ='Campus site 1'!$F165 -> 0 | G13: Déchêts directs | H13: =SUM(C36:E36) -> 7.223155 | I13: =IF($H$15=0,"",H13/$H$15) -> 0.0027087633 | L13: =IFERROR(K13/H13,"") -> 0
B14: ='Campus site 1'!C166 -> Fret ferroviaire | C14: ='Campus site 1'!$F166 -> 0 | G14: Immobilisations | H14: =SUM(C40:E40) -> 396.34573 | I14: =IF($H$15=0,"",H14/$H$15) -> 0.14863405 | L14: =IFERROR(K14/H14,"") -> 0
B15: ='Campus site 1'!C167 -> Fret maritime | C15: ='Campus site 1'!$F167 -> 0 | G15: TOTAL | H15: =SUM(H8:H14) -> 2666.5877 | I15: =SUM(I8:I14) -> 1 | K15: =SUM(K8:K14) -> 0 | L15: =IF(H15=0,"",K15/H15) -> 0
B17: ='Campus site 1'!C208 -> DEPLACEMENTS DE PERSONNES | C17: =SUM(C18:C21) -> 490.43616 | E17: =SUM(E18:E21) -> 0
B18: ='Campus site 1'!C298 -> Voiture | C18: ='Campus site 1'!$D298/1000 -> 129.3435
B19: ='Campus site 1'!C299 -> Autres modes routiers | C19: ='Campus site 1'!$D299/1000 -> 16.2
B20: ='Campus site 1'!C300 -> Train | C20: ='Campus site 1'!$D300/1000 -> 15.93378
B21: ='Campus site 1'!C301 -> Avion | C21: ='Campus site 1'!$D301/1000 -> 328.95888
B23: ='Campus site 1'!C340 -> CONSOMMABLES ET MATERIAUX | C23: =SUM(C24:C29) -> 28.703466 | E23: =SUM(E24:E29) -> 0
B24: ='Campus site 1'!C427 -> Métaux | C24: ='Campus site 1'!$E427 -> 4.156238
B25: ='Campus site 1'!C428 -> Plastiques | C25: ='Campus site 1'!$E428 -> 0
B26: ='Campus site 1'!C429 -> Verres | C26: ='Campus site 1'!$E429 -> 0
B27: ='Campus site 1'!C430 -> Papiers et cartons | C27: ='Campus site 1'!$E430 -> 18.361728
B28: ='Campus site 1'!C431 -> Produits chimiques & textiles de synthèse | C28: ='Campus site 1'!$E431 -> 0
B29: ='Campus site 1'!C432 -> Autres (produits manufacturés ou services) | C29: ='Campus site 1'!$E432 -> 6.1855
B31: ='Campus site 1'!C471 -> RESTAURANT UNIVERSITAIRE | C31: =SUM(C32:C34) -> 457.164 | E31: =SUM(E32:E34) -> 0
B32: ='Campus site 1'!C566 -> Viandes et poissons | C32: ='Campus site 1'!$D566/1000 -> 0
B33: ='Campus site 1'!C567 -> Autres produits alimentaires | C33: ='Campus site 1'!$D567/1000 -> 0
B34: ='Campus site 1'!C568 -> Repas | C34: ='Campus site 1'!$D568/1000 -> 457.164
B36: ='Campus site 1'!C610 -> DECHETS DIRECTS | C36: =SUM(C37:C38) -> 7.223155 | E36: =SUM(E37:E37) -> 0
B37: ='Campus site 1'!C645 -> Déchets | C37: ='Campus site 1'!$F645 -> 7.138915
B38: Eaux usées | C38: ='Campus site 1'!$F646 -> 0.08424
B40: ='Campus site 1'!C687 -> IMMOBILISATIONS | C40: =SUM(C41:C43) -> 396.34573 | E40: =SUM(E41:E43) -> 0
B41: ='Campus site 1'!C744 -> Bâtiments | C41: ='Campus site 1'!$D744/1000 -> 300.91073
B42: ='Campus site 1'!C745 -> Informatique | C42: ='Campus site 1'!$D745/1000 -> 95.435
B43: ='Campus site 1'!C746 -> Autres équipements | C43: ='Campus site 1'!$G736/1000 -> 0

Sheet Convertisseurs
B2: CONVERTISSEURS ENERGETIQUES
B4: Convertisseur : passage de PCS en PCI
B5: Combustible | C5: kWh PCS | D5: kWh PCI | G5: Combustible | I5: Rapport PCS / PCI
B6: Gaz Naturel | D6: =C6/I6 -> 0 | G6: Gaz naturel | I6: 1.11
B7: GPL | D7: =C7/I7 -> 0 | G7: GPL | I7: 1.09
B8: Essence | D8: =C8/I8 -> 0 | G8: Essence | I8: 1.08
B9: Diesel, fioul domestique | D9: =C9/I9 -> 0 | G9: Diesel, fioul domestique | I9: 1.07
B10: Fioul lourd | D10: =C10/I10 -> 0 | G10: Fioul lourd | I10: 1.06
B11: Charbon | D11: =C11/I11 -> 0 | G11: Charbon | I11: 1.05
B13: Convertisseur : passage de diverses unités physiques vers d'autres unités | M13: conversion des unités
B14: Unité | C14: Valeur | D14: Tep | E14: Tec | F14: Joule | G14: kWh PCI | H14: BTU | I14: m3 de gaz nat. | J14: t bois 20% hum. | M14: tep | N14: tec | O14: Joule | P14: KWh PCI | Q14: BTU | R14: m3 de gaz nat. | S14: tonne bois 20% hum
B15: Tep | D15: =$C15*M15 -> 0 | E15: =$C15*N15 -> 0 | F15: =$C15*O15 -> 0 | G15: =$C15*P15 -> 0 | H15: =$C15*Q15 -> 0 | I15: =$C15*R15 -> 0 | J15: =$C15*S15 -> 0 | L15: tep | M15: 1 | N15: =O15/O16 -> 1.4340344 | O15: 42000000000 | P15: =O15/3600000 -> 11666.667 | Q15: =O15*Q17 -> 39808351 | R15: 1200 | S15: =1/M21 -> 2.991453
B16: Tec | D16: =$C16*M16 -> 0 | E16: =$C16*N16 -> 0 | F16: =$C16*O16 -> 0 | G16: =$C16*P16 -> 0 | H16: =$C16*Q16 -> 0 | I16: =$C16*R16 -> 0 | J16: =$C16*S16 -> 0 | L16: tec | M16: =1/N15 -> 0.69733333 | N16: 1 | O16: =4.184*7000000000 -> 29288000000 | P16: =O16/3600000 -> 8135.5556 | Q16: =O16*Q17 -> 27759690 | R16: =R15/N15 -> 836.8 | S16: =1/N21 -> 2.0860399
B17: Joule | D17: =$C17*M17 -> 0 | E17: =$C17*N17 -> 0 | F17: =$C17*O17 -> 0 | G17: =$C17*P17 -> 0 | H17: =$C17*Q17 -> 0 | I17: =$C17*R17 -> 0 | J17: =$C17*S17 -> 0 | L17: Joule | M17: =1/O15 -> 2.3809524e-11 | N17: =1/O16 -> 3.4143677e-11 | O17: 1 | P17: =1/O18 -> 2.7777778e-07 | Q17: =1/O19 -> 0.00094781789 | R17: =1/O20 -> 2.8571429e-08 | S17: =1/O21 -> 7.1225071e-11
B18: kWh PCI | D18: =$C18*M18 -> 0 | E18: =$C18*N18 -> 0 | F18: =$C18*O18 -> 0 | G18: =$C18*P18 -> 0 | H18: =$C18*Q18 -> 0 | I18: =$C18*R18 -> 0 | J18: =$C18*S18 -> 0 | L18: kwh PCI | M18: =1/P15 -> 8.5714286e-05 | N18: =1/P16 -> 0.00012291724 | O18: 3600000 | P18: 1 | Q18: =1/P19 -> 3412.1444 | R18: =1/P20 -> 0.10285714 | S18: =1/P21 -> 0.00025641026
B19: BTU | D19: =$C19*M19 -> 0 | E19: =$C19*N19 -> 0 | F19: =$C19*O19 -> 0 | G19: =$C19*P19 -> 0 | H19: =$C19*Q19 -> 0 | I19: =$C19*R19 -> 0 | J19: =$C19*S19 -> 0 | L19: BTU | M19: =1/Q15 -> 2.5120357e-08 | N19: =1/Q16 -> 3.6023457e-08 | O19: 1055.055 | P19: =P15*M19 -> 0.00029307083 | Q19: 1 | R19: =1/Q20 -> 3.0144429e-05 | S19: =1/Q21 -> 7.5146368e-08
B20: m3 de Gaz Naturel | D20: =$C20*M20 -> 0 | E20: =$C20*N20 -> 0 | F20: =$C20*O20 -> 0 | G20: =$C20*P20 -> 0 | H20: =$C20*Q20 -> 0 | I20: =$C20*R20 -> 0 | J20: =$C20*S20 -> 0 | L20: m3 de gaz nat. | M20: =1/R15 -> 0.00083333333 | N20: =M20*N15 -> 0.0011950287 | O20: =O15*M20 -> 35000000 | P20: =P15*M20 -> 9.7222222 | Q20: =M20*Q15 -> 33173.626 | R20: 1 | S20: =S19*Q20 -> 0.0024928775
B21: Tonne bois 20% humidité | D21: =$C21*M21 -> 0 | E21: =$C21*N21 -> 0 | F21: =$C21*O21 -> 0 | G21: =$C21*P21 -> 0 | H21: =$C21*Q21 -> 0 | I21: =$C21*R21 -> 0 | J21: =$C21*S21 -> 0 | L21: t bois 20% humidité | M21: =P21/P15 -> 0.33428571 | N21: =P21/P16 -> 0.47937722 | O21: =P21*3600000 -> 14040000000 | P21: 3900 | Q21: =P21*Q18 -> 13307363 | R21: =1/S20 -> 401.14286 | S21: 1
B26: FUITES DE FLUIDE FRIGORIGENES
B28: Fuites : secteur Tertiaire
B29: Equipements | C29: Nombre | D29: Charge moyenne (kg fluide/unité) | E29: Taux de fuite | F29: kg émis par an
B30: Climatisation DRV (bureaux) | C30: 20 | D30: 9 | E30: 0.1 | F30: =C30*D30*E30 -> 18
B31: Climatisation armoire (baie informatique) | C31: 0 | D31: 26 | E31: 0.05 | F31: =C31*D31*E31 -> 0
B32: Climatisation Rooftop (amphi) | C32: 0 | D32: 5 | E32: 0.06 | F32: =C32*D32*E32 -> 0
B33: Autres | C33: 0 | D33: 9 | E33: 0.09 | F33: =C33*D33*E33 -> 0
B36: Fuites : secteur Tertiaire, par puissance d'équipement
B37: Puissance de l'équipement | C37: Surface refroidie (m2) | D37: Conso moyenne (kg fluide/m2) | E37: Taux de fuite | F37: Kg émis par an
B38: P < 50 kW | C38: 0 | D38: 0.3 | E38: 0.1 | F38: =C38*D38*E38 -> 0
B39: 50 < P < 350 kW | C39: 7820 | D39: 0.3 | E39: 0.05 | F39: =C39*D39*E39 -> 117.3
B40: P > 350 kW | C40: 0 | D40: 0.2 | E40: 0.05 | F40: =C40*D40*E40 -> 0
B41: Autres | C41: 0 | D41: 0.3 | E41: 0.04 | F41: =C41*D41*E41 -> 0

Sheet Feuil1
A1: 270650
A2: 240318
A3: 240753
A4: 166595
A5: 161710
A6: 110790
A7: 73553
A8: 53861
A9: 144370
A10: 177046
A11: 211146
A12: 240208
